rltk/__init__.py
rltk/__main__.py
rltk/cli.py
rltk/dataset.py
rltk/record.py
rltk/utils.py
rltk/blocking/__init__.py
rltk/blocking/_minhash_lsh.py
rltk/blocking/block.py
rltk/blocking/block_black_list.py
rltk/blocking/block_generator.py
rltk/blocking/blocking_helper.py
rltk/blocking/canopy_block_generator.py
rltk/blocking/hash_block_generator.py
rltk/blocking/sorted_neighbourhood_block_generator.py
rltk/blocking/token_block_generator.py
rltk/evaluation/__init__.py
rltk/evaluation/evaluation.py
rltk/evaluation/ground_truth.py
rltk/evaluation/trial.py
rltk/io/__init__.py
rltk/io/io_utils.py
rltk/io/adapter/__init__.py
rltk/io/adapter/dbm_key_value_adapter.py
rltk/io/adapter/hbase_key_value_adapter.py
rltk/io/adapter/key_set_adapter.py
rltk/io/adapter/key_value_adapter.py
rltk/io/adapter/leveldb_key_set_adapter.py
rltk/io/adapter/memory_key_set_adapter.py
rltk/io/adapter/memory_key_value_adapter.py
rltk/io/adapter/redis_key_set_adapter.py
rltk/io/adapter/redis_key_value_adapter.py
rltk/io/reader/__init__.py
rltk/io/reader/array_reader.py
rltk/io/reader/csv_reader.py
rltk/io/reader/dataframe_reader.py
rltk/io/reader/ground_truth_reader.py
rltk/io/reader/jsonlines_reader.py
rltk/io/reader/reader.py
rltk/io/serializer/__init__.py
rltk/io/serializer/pickle_serializer.py
rltk/io/serializer/serializer.py
rltk/io/writer/__init__.py
rltk/io/writer/ground_truth_writer.py
rltk/io/writer/writer.py
rltk/remote/__init__.py
rltk/remote/remote.py
rltk/remote/task.py
rltk/similarity/__init__.py
rltk/similarity/cosine.py
rltk/similarity/dice.py
rltk/similarity/distance.py
rltk/similarity/equal.py
rltk/similarity/hamming.py
rltk/similarity/hybrid.py
rltk/similarity/jaccard.py
rltk/similarity/jaro.py
rltk/similarity/lcs.py
rltk/similarity/levenshtein.py
rltk/similarity/metaphone.py
rltk/similarity/needleman.py
rltk/similarity/ngram.py
rltk/similarity/nysiis.py
rltk/similarity/qgram.py
rltk/similarity/soundex.py
rltk/similarity/tf_idf.py
rltk/tests/__init__.py
rltk/tests/test_blocking.py
rltk-2.0.0a20.dist-info/LICENSE
rltk-2.0.0a20.dist-info/METADATA
rltk-2.0.0a20.dist-info/WHEEL
rltk-2.0.0a20.dist-info/top_level.txt
rltk-2.0.0a20.dist-info/RECORD
