Metadata-Version: 2.1
Name: rltk
Version: 2.0.0a20
Summary: Record Linkage ToolKit
Home-page: https://github.com/usc-isi-i2/rltk
Author: USC/ISI
Author-email: yixiangy@isi.edu
License: MIT
Project-URL: Bug Tracker, https://github.com/usc-isi-i2/rltk/issues
Project-URL: Documentation, https://rltk.readthedocs.io
Project-URL: Source Code, https://github.com/usc-isi-i2/rltk
Platform: UNKNOWN
Classifier: Programming Language :: Python :: 3
Classifier: Natural Language :: English
Classifier: License :: OSI Approved :: MIT License
Classifier: Operating System :: OS Independent
Classifier: Topic :: Scientific/Engineering
Classifier: Topic :: Scientific/Engineering :: Information Analysis
Classifier: Topic :: Software Development :: Libraries
Classifier: Topic :: Software Development :: Libraries :: Python Modules
Classifier: Intended Audience :: Science/Research
Classifier: Intended Audience :: Developers
Classifier: Intended Audience :: Education
Classifier: Intended Audience :: Information Technology
